ZetcodePhpJiaochengChuyi/README.md
ZetcodePhpJiaochengChuyi/__init__.py
ZetcodePhpJiaochengChuyi/__main__.py
ZetcodePhpJiaochengChuyi/file.epub
ZetcodePhpJiaochengChuyi/index.html
ZetcodePhpJiaochengChuyi/css/__init__.py
ZetcodePhpJiaochengChuyi/css/annotations.css
ZetcodePhpJiaochengChuyi/css/main.css
ZetcodePhpJiaochengChuyi/css/normalize.css
ZetcodePhpJiaochengChuyi/css/popup.css
ZetcodePhpJiaochengChuyi/font/__init__.py
ZetcodePhpJiaochengChuyi/font/fontello.eot
ZetcodePhpJiaochengChuyi/font/fontello.svg
ZetcodePhpJiaochengChuyi/font/fontello.ttf
ZetcodePhpJiaochengChuyi/font/fontello.woff
ZetcodePhpJiaochengChuyi/img/__init__.py
ZetcodePhpJiaochengChuyi/img/annotator-glyph-sprite.png
ZetcodePhpJiaochengChuyi/img/annotator-icon-sprite.png
ZetcodePhpJiaochengChuyi/img/apple-touch-icon.png
ZetcodePhpJiaochengChuyi/img/cancelfullscreen.png
ZetcodePhpJiaochengChuyi/img/close.png
ZetcodePhpJiaochengChuyi/img/fullscreen.png
ZetcodePhpJiaochengChuyi/img/loader.gif
ZetcodePhpJiaochengChuyi/img/menu-icon.png
ZetcodePhpJiaochengChuyi/img/save.png
ZetcodePhpJiaochengChuyi/img/saved.png
ZetcodePhpJiaochengChuyi/img/settings-s.png
ZetcodePhpJiaochengChuyi/img/settings.png
ZetcodePhpJiaochengChuyi/img/star.png
ZetcodePhpJiaochengChuyi/js/__init__.py
ZetcodePhpJiaochengChuyi/js/epub.js
ZetcodePhpJiaochengChuyi/js/epub.min.js
ZetcodePhpJiaochengChuyi/js/epub.min.map
ZetcodePhpJiaochengChuyi/js/hooks.min.js
ZetcodePhpJiaochengChuyi/js/hooks.min.map
ZetcodePhpJiaochengChuyi/js/reader.js
ZetcodePhpJiaochengChuyi/js/reader.js.map
ZetcodePhpJiaochengChuyi/js/reader.min.js
ZetcodePhpJiaochengChuyi/js/reader.min.map
ZetcodePhpJiaochengChuyi/js/hooks/__init__.py
ZetcodePhpJiaochengChuyi/js/hooks/extensions/__init__.py
ZetcodePhpJiaochengChuyi/js/hooks/extensions/highlight.js
ZetcodePhpJiaochengChuyi/js/libs/__init__.py
ZetcodePhpJiaochengChuyi/js/libs/jquery.min.js
ZetcodePhpJiaochengChuyi/js/libs/localforage.min.js
ZetcodePhpJiaochengChuyi/js/libs/screenfull.js
zetcode_php_jiaocheng_chuyi-2024.3.5.0.dist-info/METADATA
zetcode_php_jiaocheng_chuyi-2024.3.5.0.dist-info/WHEEL
zetcode_php_jiaocheng_chuyi-2024.3.5.0.dist-info/entry_points.txt
zetcode_php_jiaocheng_chuyi-2024.3.5.0.dist-info/top_level.txt
zetcode_php_jiaocheng_chuyi-2024.3.5.0.dist-info/RECORD
